{"remove":{"path":"part-00000-68081bd2-59f5-4913-8372-9cfb3302d522-c000.snappy.parquet","deletionTimestamp":1653559346392,"dataChange":true,"extendedFileMetadata":true,"partitionValues":{},"size":2624}}
{"add":{"path":"part-00000-234d09c9-574a-42b1-aebc-a4540e5a47f8-c000.snappy.parquet","partitionValues":{},"size":2617,"modificationTime":1653559346545,"dataChange":true,"stats":"{\"numRecords\":1,\"minValues\":{\"account_id\":\"a1\",\"address\":\"Jakarta\",\"email\":\"anthony@somebank.com\",\"name\":\"Anthony\",\"phone_number\":\"87654321\",\"ts\":1577863800000,\"id\":\"a1globalid\",\"savings_account_id\":\"sa1\",\"card_id\":\"\"},\"maxValues\":{\"account_id\":\"a1\",\"address\":\"Jakarta\",\"email\":\"anthony@somebank.com\",\"name\":\"Anthony\",\"phone_number\":\"87654321\",\"ts\":1577863800000,\"id\":\"a1globalid\",\"savings_account_id\":\"sa1\",\"card_id\":\"\"},\"nullCount\":{\"account_id\":0,\"address\":0,\"email\":0,\"name\":0,\"phone_number\":0,\"ts\":0,\"id\":0,\"savings_account_id\":0,\"card_id\":0}}"}}
{"commitInfo":{"timestamp":1653559346550,"operation":"UPDATE","operationParameters":{"predicate":"(id#2728 = a1globalid)"},"readVersion":2,"isolationLevel":"Serializable","isBlindAppend":false,"operationMetrics":{"numRemovedFiles":"1","numCopiedRows":"0","executionTimeMs":"708","scanTimeMs":"551","numAddedFiles":"1","numUpdatedRows":"1","rewriteTimeMs":"157"},"engineInfo":"Apache-Spark/3.2.1 Delta-Lake/1.2.1","txnId":"7b87fd2f-feae-4dff-bb77-9b45a5ee811d"}}
